my_configs/__init__.py
my_configs/main.py
my_configs-0.0.1.dist-info/METADATA
my_configs-0.0.1.dist-info/WHEEL
my_configs-0.0.1.dist-info/licenses/LICENSE
my_configs-0.0.1.dist-info/RECORD
