Metadata-Version: 2.1
Name: my_configs
Version: 0.0.1
Summary: A python file manager for working with JSON configs.
Project-URL: Homepage, https://github.com/illushun/my_configs
Project-URL: Bug Tracker, https://github.com/illushun/my_configs/issues
Author: illushun
License: MIT License
Classifier: License :: OSI Approved :: MIT License
Classifier: Operating System :: OS Independent
Classifier: Programming Language :: Python :: 3
Requires-Python: >=3.7
